<open>
    <dynamicGamedata>
        <drawnCards></drawnCards>
        <playingPlayer>TestPlayer</playingPlayer>
        <plantCount>0</plantCount>
        <playerCount>0</playerCount>
        <cardsToPlant></cardsToPlant>
        <playingPlayerID>0</playingPlayerID>
        <plant1or2>1</plant1or2>
    </dynamicGamedata>
    <players>
        <player>
            <playerName>TestPlayer</playerName>
            <playerHand></playerHand>
            <plantField1></plantField1>
            <plantField2></plantField2>
            <plantField3></plantField3>
            <gold>0</gold>
            <state>Plays</state>
            <lastMethodUsed> </lastMethodUsed>
        </player>
    </players>
</open>